deepframe/MultiRunner.py
deepframe/Runner.py
deepframe/__init__.py
deepframe/losses.py
deepframe/utils.py
deepframe/Dataset/BaseDataset.py
deepframe/Dataset/__init__.py
deepframe/Dataset/transforms.py
deepframe/Dataset/utils.py
deepframe/Evaluator/BaseEvaluator.py
deepframe/Evaluator/__init__.py
deepframe/MetricLogger/BaseMetricLogger.py
deepframe/MetricLogger/__init__.py
deepframe/Model/BaseNeuralNetwork.py
deepframe/Model/__init__.py
deepframe/Model/utils.py
deepframe/Model/NeuralNetworks/Convolutional.py
deepframe/Model/NeuralNetworks/FullyConnected.py
deepframe/Model/NeuralNetworks/Recursive.py
deepframe/Model/NeuralNetworks/__init__.py
deep_learning_framework-0.1.13.dist-info/LICENSE.txt
deep_learning_framework-0.1.13.dist-info/METADATA
deep_learning_framework-0.1.13.dist-info/WHEEL
deep_learning_framework-0.1.13.dist-info/top_level.txt
deep_learning_framework-0.1.13.dist-info/RECORD
