Metadata-Version: 2.1
Name: deep-learning-framework
Version: 0.1.13
Home-page: https://github.com/theorieken/deep-learning-framework
Author: Theo Rieken
Author-email: mail@theorieken.de
License: MIT
Keywords: deep learning
License-File: LICENSE.txt
Requires-Dist: torch
Requires-Dist: cycler
Requires-Dist: matplotlib
Requires-Dist: numpy
Requires-Dist: pandas
Requires-Dist: wandb
Requires-Dist: torchvision
Requires-Dist: scipy
Requires-Dist: plotly
Requires-Dist: scikit-learn
